cdsapi/__init__.py
cdsapi/api.py
cdsapi-0.7.4.dist-info/LICENSE.txt
cdsapi-0.7.4.dist-info/METADATA
cdsapi-0.7.4.dist-info/WHEEL
cdsapi-0.7.4.dist-info/top_level.txt
cdsapi-0.7.4.dist-info/zip-safe
cdsapi-0.7.4.dist-info/RECORD
