Metadata-Version: 2.1
Name: cdsapi
Version: 0.7.4
Summary: Climate Data Store API
Home-page: https://github.com/ecmwf/cdsapi
Author: ECMWF
Author-email: software.support@ecmwf.int
License: Apache 2.0
Classifier: Development Status :: 4 - Beta
Classifier: Intended Audience :: Developers
Classifier: Programming Language :: Python
Classifier: Programming Language :: Python :: 3
Classifier: Programming Language :: Python :: 3.8
Classifier: Programming Language :: Python :: 3.9
Classifier: Programming Language :: Python :: 3.10
Classifier: Programming Language :: Python :: 3.11
Classifier: Programming Language :: Python :: 3.12
Classifier: Programming Language :: Python :: 3.13
Classifier: Programming Language :: Python :: Implementation :: CPython
Classifier: Programming Language :: Python :: Implementation :: PyPy
Classifier: Operating System :: OS Independent
Requires-Python: >=3.8
License-File: LICENSE.txt
Requires-Dist: cads-api-client>=1.4.7
Requires-Dist: requests>=2.5.0
Requires-Dist: tqdm
